qurry/version.py
qurry/__init__.py
qurry/boorust.abi3.so
qurry/exceptions.py
qurry/VERSION.txt
qurry/qurrent/__init__.py
qurry/qurrent/hadamard_test/analysis.py
qurry/qurrent/hadamard_test/arguments.py
qurry/qurrent/hadamard_test/__init__.py
qurry/qurrent/hadamard_test/experiment.py
qurry/qurrent/hadamard_test/qurry.py
qurry/qurrent/randomized_measure_v1/analysis.py
qurry/qurrent/randomized_measure_v1/arguments.py
qurry/qurrent/randomized_measure_v1/__init__.py
qurry/qurrent/randomized_measure_v1/experiment.py
qurry/qurrent/randomized_measure_v1/utils.py
qurry/qurrent/randomized_measure_v1/qurry.py
qurry/qurrent/classical_shadow/analysis.py
qurry/qurrent/classical_shadow/arguments.py
qurry/qurrent/classical_shadow/__init__.py
qurry/qurrent/classical_shadow/experiment.py
qurry/qurrent/classical_shadow/utils.py
qurry/qurrent/classical_shadow/qurry.py
qurry/qurrent/randomized_measure/analysis.py
qurry/qurrent/randomized_measure/arguments.py
qurry/qurrent/randomized_measure/__init__.py
qurry/qurrent/randomized_measure/experiment.py
qurry/qurrent/randomized_measure/utils.py
qurry/qurrent/randomized_measure/qurry.py
qurry/tools/command.py
qurry/tools/qiskit_version.py
qurry/tools/__init__.py
qurry/tools/parallelmanager.py
qurry/tools/progressbar.py
qurry/tools/except_decorator.py
qurry/tools/datetime.py
qurry/tools/backend/__init__.py
qurry/tools/backend/import_simulator.py
qurry/tools/backend/utils.py
qurry/tools/backend/env_check.py
qurry/tools/backend/import_fake.py
qurry/tools/backend/backend_manager.py
qurry/qurrium/__init__.py
qurry/qurrium/qurrium.py
qurry/qurrium/analysis/analysis.py
qurry/qurrium/analysis/__init__.py
qurry/qurrium/runner/runner.py
qurry/qurrium/runner/bracketrunner.py
qurry/qurrium/runner/__init__.py
qurry/qurrium/runner/utils.py
qurry/qurrium/runner/accesor.py
qurry/qurrium/runner/ibmruntime_runner.py
qurry/qurrium/multimanager/arguments.py
qurry/qurrium/multimanager/__init__.py
qurrium-0.13.0.dist-info/RECORD
qurrium-0.13.0.dist-info/WHEEL
qurrium-0.13.0.dist-info/top_level.txt
qurrium-0.13.0.dist-info/METADATA
qurrium-0.13.0.dist-info/licenses/LICENSE
