Metadata-Version: 2.4
Name: qurrium
Version: 0.13.0
Summary: Qurrium 📏 - The Measuring Tool for Renyi Entropy, Loschmidt Echo, and Magnetization Squared, The Library of Some Common Cases
Author-email: Huai-Chung Chang <harui2019@proton.me>
Project-URL: Issues, https://github.com/qurrium/qurrium/issues
Project-URL: Homepage, https://github.com/qurrium/qurrium
Project-URL: Documentation, https://docs.qurrium.org
Classifier: Intended Audience :: Science/Research
Classifier: Intended Audience :: Developers
Classifier: License :: OSI Approved :: Apache Software License
Classifier: Operating System :: MacOS
Classifier: Operating System :: POSIX :: Linux
Classifier: Operating System :: Microsoft :: Windows
Classifier: Programming Language :: Python :: 3 :: Only
Classifier: Programming Language :: Python :: 3.9
Classifier: Programming Language :: Python :: 3.10
Classifier: Programming Language :: Python :: 3.11
Classifier: Programming Language :: Python :: 3.12
Classifier: Programming Language :: Python :: 3.13
Classifier: Programming Language :: Python :: Implementation :: CPython
Classifier: Topic :: Scientific/Engineering :: Physics
Requires-Python: >=3.9
License-File: LICENSE
Requires-Dist: qiskit>=0.45.0
Requires-Dist: requests
Requires-Dist: tqdm
Dynamic: license-file
